pyridl/__init__.py
pyridl/dataset.py
pyridl/iridl_utils.py
pyridl/source.py
pyridl/sourcetree.py
pyridl-0.1.0.dist-info/LICENSE
pyridl-0.1.0.dist-info/METADATA
pyridl-0.1.0.dist-info/WHEEL
pyridl-0.1.0.dist-info/top_level.txt
pyridl-0.1.0.dist-info/RECORD
