Metadata-Version: 2.1
Name: pyridl
Version: 0.1.0
Summary: mini, unofficial IRI Data Library API 
Home-page: https://bitbucket.org/hallkjc01/pyridl
Author: Kyle Hall - IRICS
Author-email: kjhall@iri.columbia.edu
License: UNKNOWN
Platform: UNKNOWN
Classifier: Programming Language :: Python :: 3
Classifier: License :: OSI Approved :: GNU General Public License v3 or later (GPLv3+)
Classifier: Operating System :: OS Independent
Requires-Python: >=3.0
